{
    "@type": "Collection",
    "member": [
        {
            "space": 7,
            "origin": "https://s3.amazonaws.com/NARAprodstorage/lz/dc-metro/rg-011/299798/RIT-Batch23/178331497/178331497-001_ma.jpg",
            "string1": "chapterday",
            "string2": "178331497",
            "number1": 18
        },
        {
            "space": 7,
            "origin": "https://s3.amazonaws.com/NARAprodstorage/lz/dc-metro/rg-011/299798/RIT-Batch23/178331497/178331497-002_ma.jpg",
            "string1": "chapterday",
            "string2": "178331497",
            "number1": 19
        },
        {
            "space": 7,
            "origin": "https://s3.amazonaws.com/NARAprodstorage/lz/dc-metro/rg-011/299798/RIT-Batch23/178331497/178331497-003_ma.jpg",
            "string1": "chapterday",
            "string2": "178331497",
            "number1": 20
        },
        {
            "space": 7,
            "origin": "https://s3.amazonaws.com/NARAprodstorage/lz/dc-metro/rg-011/299798/RIT-Batch23/178331497/178331497-004_ma.jpg",
            "string1": "chapterday",
            "string2": "178331497",
            "number1": 21
        },
        {
            "space": 7,
            "origin": "https://s3.amazonaws.com/NARAprodstorage/lz/dc-metro/rg-011/299798/RIT-Batch23/178331497/178331497-005_ma.jpg",
            "string1": "chapterday",
            "string2": "178331497",
            "number1": 22
        },
        {
            "space": 7,
            "origin": "https://s3.amazonaws.com/NARAprodstorage/lz/dc-metro/rg-011/299798/RIT-Batch23/178331497/178331497-006_ma.jpg",
            "string1": "chapterday",
            "string2": "178331497",
            "number1": 23
        },
        {
            "space": 7,
            "origin": "https://s3.amazonaws.com/NARAprodstorage/lz/dc-metro/rg-011/299798/RIT-Batch23/178331497/178331497-007_ma.jpg",
            "string1": "chapterday",
            "string2": "178331497",
            "number1": 24
        },
        {
            "space": 7,
            "origin": "https://s3.amazonaws.com/NARAprodstorage/lz/dc-metro/rg-011/299798/RIT-Batch23/178331497/178331497-009_ma.jpg",
            "string1": "chapterday",
            "string2": "178331497",
            "number1": 26
        },
        {
            "space": 7,
            "origin": "https://s3.amazonaws.com/NARAprodstorage/lz/dc-metro/rg-011/299798/RIT-Batch23/178331497/178331497-010_ma.jpg",
            "string1": "chapterday",
            "string2": "178331497",
            "number1": 27
        },
        {
            "space": 7,
            "origin": "https://s3.amazonaws.com/NARAprodstorage/lz/dc-metro/rg-011/299798/RIT-Batch23/178331497/178331497-011_ma.jpg",
            "string1": "chapterday",
            "string2": "178331497",
            "number1": 28
        },
        {
            "space": 7,
            "origin": "https://s3.amazonaws.com/NARAprodstorage/lz/dc-metro/rg-011/299798/RIT-Batch23/178331497/178331497-012_ma.jpg",
            "string1": "chapterday",
            "string2": "178331497",
            "number1": 29
        },
        {
            "space": 7,
            "origin": "https://s3.amazonaws.com/NARAprodstorage/lz/dc-metro/rg-011/299798/RIT-Batch23/178331497/178331497-013_ma.jpg",
            "string1": "chapterday",
            "string2": "178331497",
            "number1": 30
        },
        {
            "space": 7,
            "origin": "https://s3.amazonaws.com/NARAprodstorage/lz/dc-metro/rg-011/299798/RIT-Batch23/178331497/178331497-014_ma.jpg",
            "string1": "chapterday",
            "string2": "178331497",
            "number1": 31
        },
        {
            "space": 7,
            "origin": "https://s3.amazonaws.com/NARAprodstorage/lz/dc-metro/rg-011/299798/RIT-Batch23/178331497/178331497-015_ma.jpg",
            "string1": "chapterday",
            "string2": "178331497",
            "number1": 32
        },
        {
            "space": 7,
            "origin": "https://s3.amazonaws.com/NARAprodstorage/lz/dc-metro/rg-011/299798/RIT-Batch23/178331497/178331497-016_ma.jpg",
            "string1": "chapterday",
            "string2": "178331497",
            "number1": 33
        },
        {
            "space": 7,
            "origin": "https://s3.amazonaws.com/NARAprodstorage/lz/dc-metro/rg-011/299798/RIT-Batch23/178331497/178331497-017_ma.jpg",
            "string1": "chapterday",
            "string2": "178331497",
            "number1": 34
        }
    ]
}