{
    "@type": "Collection",
    "member": [
        {
            "space": 8,
            "origin": "https://s3.amazonaws.com/NARAprodstorage/lz/dc-metro/rg-011/299798/RIT-Batch-24/178931099/178931099-001_ma.jpg",
            "string1": "digitreaties",
            "string2": "178931099",
            "number1": 5
        },
        {
            "space": 8,
            "origin": "https://s3.amazonaws.com/NARAprodstorage/lz/dc-metro/rg-011/299798/RIT-Batch-24/178931099/178931099-002_ma.jpg",
            "string1": "digitreaties",
            "string2": "178931099",
            "number1": 6
        },
        {
            "space": 8,
            "origin": "https://s3.amazonaws.com/NARAprodstorage/lz/dc-metro/rg-011/299798/RIT-Batch-24/178931099/178931099-003_ma.jpg",
            "string1": "digitreaties",
            "string2": "178931099",
            "number1": 7
        },
        {
            "space": 8,
            "origin": "https://s3.amazonaws.com/NARAprodstorage/lz/dc-metro/rg-011/299798/RIT-Batch-24/178931099/178931099-004_ma.jpg",
            "string1": "digitreaties",
            "string2": "178931099",
            "number1": 8
        }
    ]
}