{
    "@type": "Collection",
    "member": [
        {
            "space": 7,
            "origin": "https://s3.amazonaws.com/NARAprodstorage/lz/dc-metro/rg-011/299798/RIT-Batch-24A/183393121/183393121-001_ma.jpg",
            "string1": "chapterday",
            "string2": "183393121",
            "number1": 3
        },
        {
            "space": 7,
            "origin": "https://s3.amazonaws.com/NARAprodstorage/lz/dc-metro/rg-011/299798/RIT-Batch-24A/183393121/183393121-002_ma.jpg",
            "string1": "chapterday",
            "string2": "183393121",
            "number1": 4
        }
    ]
}