{
    "@type": "Collection",
    "member": [
        {
            "space": 8,
            "origin": "https://s3.amazonaws.com/NARAprodstorage/lz/dc-metro/rg-011/299798/596331/596331-001_ma.jpg",
            "string1": "digitreaties",
            "string2": "596331",
            "number1": 2
        },
        {
            "space": 8,
            "origin": "https://s3.amazonaws.com/NARAprodstorage/lz/dc-metro/rg-011/299798/596331/596331-002_ma.jpg",
            "string1": "digitreaties",
            "string2": "596331",
            "number1": 4
        }
    ]
}